yenepaypy/__init__.py
yenepaypy/main.py
yenepaypy/signer.py
yenepaypy-0.1.2.dist-info/LICENSE
yenepaypy-0.1.2.dist-info/METADATA
yenepaypy-0.1.2.dist-info/WHEEL
yenepaypy-0.1.2.dist-info/top_level.txt
yenepaypy-0.1.2.dist-info/RECORD
