Metadata-Version: 2.1
Name: yenepaypy
Version: 0.1.2
Summary: A simple and easily integrable yenepay library for your python code
Home-page: https://github.com/Saikyo0/yenepaypyth
Author: Saikyo0
Author-email: tmansaikyou@gmail.com
License: GNU General Public License
Classifier: Development Status :: 4 - Beta
Classifier: Operating System :: Microsoft :: Windows :: Windows 7
Classifier: Operating System :: Microsoft :: Windows :: Windows 8
Classifier: Operating System :: Microsoft :: Windows :: Windows 8.1
Classifier: Operating System :: Microsoft :: Windows :: Windows 10
Classifier: Operating System :: POSIX :: Linux
Classifier: Operating System :: Microsoft :: Windows :: Windows 11
Classifier: License :: OSI Approved :: GNU General Public License v3 (GPLv3)
Classifier: Operating System :: POSIX :: Linux
Classifier: Programming Language :: Python :: 2
Classifier: Programming Language :: Python :: 2.7
Classifier: Programming Language :: Python :: 3
Classifier: Programming Language :: Python :: 3.4
Classifier: Programming Language :: Python :: 3.5
License-File: LICENSE
Requires-Dist: pyOpenSSL
Requires-Dist: requests
